{".class": "MypyFile", "_fullname": "config", "is_partial_stub_package": false, "is_stub": false, "names": {".class": "SymbolTable", "BaseConfig": {".class": "SymbolTableNode", "kind": "Gdef", "node": {".class": "TypeInfo", "_promote": null, "abstract_attributes": [], "bases": ["builtins.object"], "declared_metaclass": null, "defn": {".class": "ClassDef", "fullname": "config.BaseConfig", "name": "BaseConfig", "type_vars": []}, "flags": [], "fullname": "config.BaseConfig", "metaclass_type": null, "metadata": {}, "module_name": "config", "mro": ["config.BaseConfig", "builtins.object"], "names": {".class": "SymbolTable", "HOST": {".class": "SymbolTableNode", "kind": "Mdef", "node": {".class": "Var", "flags": ["is_initialized_in_class"], "fullname": "config.BaseConfig.HOST", "name": "HOST", "type": "builtins.str"}}, "PAGE_ITEMS": {".class": "SymbolTableNode", "kind": "Mdef", "node": {".class": "Var", "flags": ["is_initialized_in_class"], "fullname": "config.BaseConfig.PAGE_ITEMS", "name": "PAGE_ITEMS", "type": "builtins.int"}}, "RESTFUL_JSON": {".class": "SymbolTableNode", "kind": "Mdef", "node": {".class": "Var", "flags": ["is_initialized_in_class"], "fullname": "config.BaseConfig.RESTFUL_JSON", "name": "RESTFUL_JSON", "type": {".class": "Instance", "args": ["builtins.str", "builtins.bool"], "type_ref": "builtins.dict"}}}, "SECRET_KEY": {".class": "SymbolTableNode", "kind": "Mdef", "node": {".class": "Var", "flags": ["is_initialized_in_class"], "fullname": "config.BaseConfig.SECRET_KEY", "name": "SECRET_KEY", "type": "builtins.str"}}, "SQLALCHEMY_DATABASE_URI": {".class": "SymbolTableNode", "kind": "Mdef", "node": {".class": "Var", "flags": ["is_initialized_in_class"], "fullname": "config.BaseConfig.SQLALCHEMY_DATABASE_URI", "name": "SQLALCHEMY_DATABASE_URI", "type": "builtins.str"}}, "SQLALCHEMY_TRACK_MODIFICATIONS": {".class": "SymbolTableNode", "kind": "Mdef", "node": {".class": "Var", "flags": ["is_initialized_in_class"], "fullname": "config.BaseConfig.SQLALCHEMY_TRACK_MODIFICATIONS", "name": "SQLALCHEMY_TRACK_MODIFICATIONS", "type": "builtins.bool"}}, "UPLOAD_FOLDER": {".class": "SymbolTableNode", "kind": "Mdef", "node": {".class": "Var", "flags": ["is_initialized_in_class"], "fullname": "config.BaseConfig.UPLOAD_FOLDER", "name": "UPLOAD_FOLDER", "type": "builtins.str"}}}, "tuple_type": null, "type_vars": [], "typeddict_type": null}}, "ProConfig": {".class": "SymbolTableNode", "kind": "Gdef", "node": {".class": "TypeInfo", "_promote": null, "abstract_attributes": [], "bases": ["builtins.object"], "declared_metaclass": null, "defn": {".class": "ClassDef", "fullname": "config.ProConfig", "name": "ProConfig", "type_vars": []}, "flags": [], "fullname": "config.ProConfig", "metaclass_type": null, "metadata": {}, "module_name": "config", "mro": ["config.ProConfig", "builtins.object"], "names": {".class": "SymbolTable", "HOST": {".class": "SymbolTableNode", "kind": "Mdef", "node": {".class": "Var", "flags": ["is_initialized_in_class"], "fullname": "config.ProConfig.HOST", "name": "HOST", "type": "builtins.str"}}, "PAGE_ITEMS": {".class": "SymbolTableNode", "kind": "Mdef", "node": {".class": "Var", "flags": ["is_initialized_in_class"], "fullname": "config.ProConfig.PAGE_ITEMS", "name": "PAGE_ITEMS", "type": "builtins.int"}}, "RESTFUL_JSON": {".class": "SymbolTableNode", "kind": "Mdef", "node": {".class": "Var", "flags": ["is_initialized_in_class"], "fullname": "config.ProConfig.RESTFUL_JSON", "name": "RESTFUL_JSON", "type": {".class": "Instance", "args": ["builtins.str", "builtins.bool"], "type_ref": "builtins.dict"}}}, "SECRET_KEY": {".class": "SymbolTableNode", "kind": "Mdef", "node": {".class": "Var", "flags": ["is_initialized_in_class"], "fullname": "config.ProConfig.SECRET_KEY", "name": "SECRET_KEY", "type": "builtins.str"}}, "SQLALCHEMY_DATABASE_URI": {".class": "SymbolTableNode", "kind": "Mdef", "node": {".class": "Var", "flags": ["is_initialized_in_class"], "fullname": "config.ProConfig.SQLALCHEMY_DATABASE_URI", "name": "SQLALCHEMY_DATABASE_URI", "type": "builtins.str"}}, "SQLALCHEMY_TRACK_MODIFICATIONS": {".class": "SymbolTableNode", "kind": "Mdef", "node": {".class": "Var", "flags": ["is_initialized_in_class"], "fullname": "config.ProConfig.SQLALCHEMY_TRACK_MODIFICATIONS", "name": "SQLALCHEMY_TRACK_MODIFICATIONS", "type": "builtins.bool"}}, "UPLOAD_FOLDER": {".class": "SymbolTableNode", "kind": "Mdef", "node": {".class": "Var", "flags": ["is_initialized_in_class"], "fullname": "config.ProConfig.UPLOAD_FOLDER", "name": "UPLOAD_FOLDER", "type": "builtins.str"}}}, "tuple_type": null, "type_vars": [], "typeddict_type": null}}, "TestConfig": {".class": "SymbolTableNode", "kind": "Gdef", "node": {".class": "TypeInfo", "_promote": null, "abstract_attributes": [], "bases": ["builtins.object"], "declared_metaclass": null, "defn": {".class": "ClassDef", "fullname": "config.TestConfig", "name": "TestConfig", "type_vars": []}, "flags": [], "fullname": "config.TestConfig", "metaclass_type": null, "metadata": {}, "module_name": "config", "mro": ["config.TestConfig", "builtins.object"], "names": {".class": "SymbolTable", "PAGE_ITEMS": {".class": "SymbolTableNode", "kind": "Mdef", "node": {".class": "Var", "flags": ["is_initialized_in_class"], "fullname": "config.TestConfig.PAGE_ITEMS", "name": "PAGE_ITEMS", "type": "builtins.int"}}, "RESTFUL_JSON": {".class": "SymbolTableNode", "kind": "Mdef", "node": {".class": "Var", "flags": ["is_initialized_in_class"], "fullname": "config.TestConfig.RESTFUL_JSON", "name": "RESTFUL_JSON", "type": {".class": "Instance", "args": ["builtins.str", "builtins.bool"], "type_ref": "builtins.dict"}}}, "SECRET_KEY": {".class": "SymbolTableNode", "kind": "Mdef", "node": {".class": "Var", "flags": ["is_initialized_in_class"], "fullname": "config.TestConfig.SECRET_KEY", "name": "SECRET_KEY", "type": "builtins.str"}}, "SQLALCHEMY_DATABASE_URI": {".class": "SymbolTableNode", "kind": "Mdef", "node": {".class": "Var", "flags": ["is_initialized_in_class"], "fullname": "config.TestConfig.SQLALCHEMY_DATABASE_URI", "name": "SQLALCHEMY_DATABASE_URI", "type": "builtins.str"}}, "SQLALCHEMY_TRACK_MODIFICATIONS": {".class": "SymbolTableNode", "kind": "Mdef", "node": {".class": "Var", "flags": ["is_initialized_in_class"], "fullname": "config.TestConfig.SQLALCHEMY_TRACK_MODIFICATIONS", "name": "SQLALCHEMY_TRACK_MODIFICATIONS", "type": "builtins.bool"}}, "UPLOAD_FOLDER": {".class": "SymbolTableNode", "kind": "Mdef", "node": {".class": "Var", "flags": ["is_initialized_in_class"], "fullname": "config.TestConfig.UPLOAD_FOLDER", "name": "UPLOAD_FOLDER", "type": "builtins.str"}}}, "tuple_type": null, "type_vars": [], "typeddict_type": null}}, "__doc__": {".class": "SymbolTableNode", "kind": "Gdef", "node": {".class": "Var", "flags": [], "fullname": "config.__doc__", "name": "__doc__", "type": "builtins.str"}}, "__file__": {".class": "SymbolTableNode", "kind": "Gdef", "node": {".class": "Var", "flags": [], "fullname": "config.__file__", "name": "__file__", "type": "builtins.str"}}, "__name__": {".class": "SymbolTableNode", "kind": "Gdef", "node": {".class": "Var", "flags": [], "fullname": "config.__name__", "name": "__name__", "type": "builtins.str"}}, "__package__": {".class": "SymbolTableNode", "kind": "Gdef", "node": {".class": "Var", "flags": [], "fullname": "config.__package__", "name": "__package__", "type": "builtins.str"}}, "config": {".class": "SymbolTableNode", "kind": "Gdef", "node": {".class": "Var", "flags": [], "fullname": "config.config", "name": "config", "type": {".class": "Instance", "args": ["builtins.str", {".class": "CallableType", "arg_kinds": [], "arg_names": [], "arg_types": [], "bound_args": [null], "def_extras": {"first_arg": "self"}, "fallback": "builtins.type", "implicit": false, "is_ellipsis_args": false, "name": null, "ret_type": "builtins.object", "variables": []}], "type_ref": "builtins.dict"}}}, "os": {".class": "SymbolTableNode", "cross_ref": "os", "kind": "ModuleRef"}}, "path": "/home/neo/repos/rest-blog/config.py"}
